my_package_for_wow_ai/__init__.py
my_package_for_wow_ai-0.0.1.dist-info/METADATA
my_package_for_wow_ai-0.0.1.dist-info/WHEEL
my_package_for_wow_ai-0.0.1.dist-info/top_level.txt
my_package_for_wow_ai-0.0.1.dist-info/RECORD
