Metadata-Version: 2.1
Name: my-package-for-wow-ai
Version: 0.0.1
Summary: A simple package to add two numbers
Home-page: UNKNOWN
Author: cuong
Author-email: your.email@example.com
License: UNKNOWN
Platform: UNKNOWN
